iotile_transport_jlink/__init__.py
iotile_transport_jlink/devices.py
iotile_transport_jlink/jlink.py
iotile_transport_jlink/jlink_background.py
iotile_transport_jlink/multiplexers.py
iotile_transport_jlink/structures.py
iotile_transport_jlink/data/__init__.py
iotile_transport_jlink/data/flash_forensics.bin
iotile_transport_jlink/data/flash_forensics_config.py
iotile_transport_jlink-1.2.0.dist-info/LICENSE.MD
iotile_transport_jlink-1.2.0.dist-info/METADATA
iotile_transport_jlink-1.2.0.dist-info/WHEEL
iotile_transport_jlink-1.2.0.dist-info/entry_points.txt
iotile_transport_jlink-1.2.0.dist-info/top_level.txt
iotile_transport_jlink-1.2.0.dist-info/RECORD
