Metadata-Version: 2.1
Name: iotile-transport-jlink
Version: 1.2.0
Summary: IOTile JLINK Transport Plugin
Home-page: http://github.com/iotile/coretools
Author: Arch
Author-email: info@arch-iot.com
License: LGPLv3
Keywords: iotile,arch,embedded,hardware,firmware
Platform: UNKNOWN
Classifier: Programming Language :: Python
Classifier: Development Status :: 2 - Pre-Alpha
Classifier: License :: OSI Approved :: GNU Library or Lesser General Public License (LGPL)
Classifier: Operating System :: OS Independent
Classifier: Programming Language :: Python :: 3
Classifier: Programming Language :: Python :: 3.7
Classifier: Programming Language :: Python :: 3.8
Classifier: Programming Language :: Python :: 3.9
Classifier: Topic :: Software Development :: Libraries :: Python Modules
Requires-Python: >=3.7,<4
Requires-Dist: iotile-core (>=5.2)
Requires-Dist: pylink-square (>=0.10)
Requires-Dist: pylibftdi (>=0.19)
